gentimer/__init__.py
gentimer/_typed.py
gentimer/timer_qt.py
gentimer/timer_sched.py
gentimer/timer_tk.py
gentimer/timer_wx.py
gentimer-0.1.1.dist-info/WHEEL
gentimer-0.1.1.dist-info/METADATA
gentimer-0.1.1.dist-info/RECORD
