Metadata-Version: 2.1
Name: gentimer
Version: 0.1.1
Summary: Utility to make generator to be consumed in event-loop timer
Home-page: https://github.com/teamikl/gentimer
License: MIT
Author: teamikl
Requires-Python: >=3.7,<4.0
Classifier: License :: OSI Approved :: MIT License
Classifier: Programming Language :: Python :: 3
Classifier: Programming Language :: Python :: 3.7
Classifier: Programming Language :: Python :: 3.8
Project-URL: Repository, https://github.com/teamikl/gentimer
